filearchive
