Metadata-Version: 1.0
Name: filearchive
Version: 1.1.1
Summary: Python module to work with file archives
Home-page: http://github.com/ActiveState/filearchive
Author: Sridhar Ratnakumar
Author-email: github@srid.name
License: MIT
Platform: UNKNOWN
